aqueduct_executor/__init__.py
aqueduct_executor/migrators/__init__.py
aqueduct_executor/migrators/artifact_migration_000016/__init__.py
aqueduct_executor/migrators/artifact_migration_000016/execute.py
aqueduct_executor/migrators/artifact_migration_000016/main.py
aqueduct_executor/migrators/artifact_migration_000016/spec.py
aqueduct_executor/migrators/backfill_python_type_000022/__init__.py
aqueduct_executor/migrators/backfill_python_type_000022/execute.py
aqueduct_executor/migrators/backfill_python_type_000022/main.py
aqueduct_executor/migrators/backfill_python_type_000022/serialize.py
aqueduct_executor/migrators/backfill_python_type_000022/spec.py
aqueduct_executor/migrators/parameter_val_type_inference_000019/__init__.py
aqueduct_executor/migrators/parameter_val_type_inference_000019/execute.py
aqueduct_executor/migrators/parameter_val_type_inference_000019/main.py
aqueduct_executor/migrators/parameter_val_type_inference_000019/serialize.py
aqueduct_executor/migrators/parameter_val_type_inference_000019/spec.py
aqueduct_executor/operators/__init__.py
aqueduct_executor/operators/airflow/__init__.py
aqueduct_executor/operators/airflow/execute.py
aqueduct_executor/operators/airflow/main.py
aqueduct_executor/operators/airflow/spec.py
aqueduct_executor/operators/connectors/__init__.py
aqueduct_executor/operators/connectors/data/__init__.py
aqueduct_executor/operators/connectors/data/athena.py
aqueduct_executor/operators/connectors/data/azure_sql.py
aqueduct_executor/operators/connectors/data/bigquery.py
aqueduct_executor/operators/connectors/data/common.py
aqueduct_executor/operators/connectors/data/config.py
aqueduct_executor/operators/connectors/data/connector.py
aqueduct_executor/operators/connectors/data/execute.py
aqueduct_executor/operators/connectors/data/extract.py
aqueduct_executor/operators/connectors/data/gcs.py
aqueduct_executor/operators/connectors/data/load.py
aqueduct_executor/operators/connectors/data/main.py
aqueduct_ml-0.3.6.dist-info/METADATA
aqueduct_ml-0.3.6.dist-info/WHEEL
aqueduct_ml-0.3.6.dist-info/top_level.txt
aqueduct_ml-0.3.6.dist-info/RECORD
